<?xml version="1.0" ?>
<!DOCTYPE PubmedArticleSet PUBLIC "-//NLM//DTD PubMedArticle, 1st January 2019//EN" "https://dtd.nlm.nih.gov/ncbi/pubmed/out/pubmed_190101.dtd">
<PubmedArticleSet>
<PubmedArticle>
    <MedlineCitation Status="MEDLINE" Owner="NLM">
        <PMID Version="1">15456630</PMID>
        <DateCompleted>
            <Year>2005</Year>
            <Month>04</Month>
            <Day>18</Day>
        </DateCompleted>
        <DateRevised>
            <Year>2004</Year>
            <Month>09</Month>
            <Day>30</Day>
        </DateRevised>
        <Article PubModel="Print">
            <Journal>
                <ISSN IssnType="Print">0163-5581</ISSN>
                <JournalIssue CitedMedium="Print">
                    <Volume>49</Volume>
                    <Issue>1</Issue>
                    <PubDate>
                        <Year>2004</Year>
                    </PubDate>
                </JournalIssue>
                <Title>Nutrition and cancer</Title>
                <ISOAbbreviation>Nutr Cancer</ISOAbbreviation>
            </Journal>
            <ArticleTitle>Weight change and the risk of late-onset breast cancer in the original Framingham cohort.</ArticleTitle>
            <Pagination>
                <MedlinePgn>7-13</MedlinePgn>
            </Pagination>
            <Abstract>
                <AbstractText Label="OBJECTIVE" NlmCategory="OBJECTIVE">Adult weight gain has been associated with a twofold risk of postmenopausal breast cancer. Data are limited regarding whether weight gain at specific periods of marked changes in estrogen- and insulin-related hormones have different risk associations. This study assesses the relation of adult weight change overall and at specific, hormonally relevant times with diagnosis of a first breast cancer after age 55 (late onset).</AbstractText>
                <AbstractText Label="METHODS" NlmCategory="METHODS">Framingham study data were used to assess premenopausal (25-44 yr), perimenopausal (45-55 yr), postmenopausal (after 55 yr), and adult lifetime (from 25 yr) weight change in relation to late-onset breast cancer in 2,873 women followed for up to 48 yr, with 206 late-onset breast cancers.</AbstractText>
                <AbstractText Label="RESULTS" NlmCategory="RESULTS">Adult lifetime weight gain was associated with an increased risk of late-onset breast cancer (P trend = 0.046). Weight gain during specific time periods was not associated with breast cancer. Data suggested a possible decreased risk of breast cancer with weight loss from ages 25 to 44 and 45 to 55 yr (relative risk = 0.4 [0.2-1.2] and 0.5 [0.3-0.9], respectively).</AbstractText>
                <AbstractText Label="CONCLUSION" NlmCategory="CONCLUSIONS">These data confirm prior reports of an association between adult lifetime weight gain and increased risk of late-onset breast cancer and support current recommendations to avoid adult weight gain.</AbstractText>
            </Abstract>
            <AuthorList CompleteYN="Y">
                <Author ValidYN="Y">
                    <LastName>Radimer</LastName>
                    <ForeName>Kathy L</ForeName>
                    <Initials>KL</Initials>
                    <AffiliationInfo>
                        <Affiliation>Division of Health and Nutrition Examination Surveys, National Center for Health Statistics, Centers for Disease Control and Prevention, Hyattsville, MD 20782, USA. kir5@cdc.gov</Affiliation>
                    </AffiliationInfo>
                </Author>
                <Author ValidYN="Y">
                    <LastName>Ballard-Barbash</LastName>
                    <ForeName>Rachel</ForeName>
                    <Initials>R</Initials>
                </Author>
                <Author ValidYN="Y">
                    <LastName>Miller</LastName>
                    <ForeName>Jeremy S</ForeName>
                    <Initials>JS</Initials>
                </Author>
                <Author ValidYN="Y">
                    <LastName>Fay</LastName>
                    <ForeName>Michael P</ForeName>
                    <Initials>MP</Initials>
                </Author>
                <Author ValidYN="Y">
                    <LastName>Schatzkin</LastName>
                    <ForeName>Arthur</ForeName>
                    <Initials>A</Initials>
                </Author>
                <Author ValidYN="Y">
                    <LastName>Troiano</LastName>
                    <ForeName>Richard</ForeName>
                    <Initials>R</Initials>
                </Author>
                <Author ValidYN="Y">
                    <LastName>Kreger</LastName>
                    <ForeName>Bernard E</ForeName>
                    <Initials>BE</Initials>
                </Author>
                <Author ValidYN="Y">
                    <LastName>Splansky</LastName>
                    <ForeName>Greta Lee</ForeName>
                    <Initials>GL</Initials>
                </Author>
            </AuthorList>
            <Language>eng</Language>
            <PublicationTypeList>
                <PublicationType UI="D016428">Journal Article</PublicationType>
            </PublicationTypeList>
        </Article>
        <MedlineJournalInfo>
            <Country>United States</Country>
            <MedlineTA>Nutr Cancer</MedlineTA>
            <NlmUniqueID>7905040</NlmUniqueID>
            <ISSNLinking>0163-5581</ISSNLinking>
        </MedlineJournalInfo>
        <CitationSubset>IM</CitationSubset>
        <MeshHeadingList>
            <MeshHeading>
                <DescriptorName UI="D000328" MajorTopicYN="N">Adult</DescriptorName>
            </MeshHeading>
            <MeshHeading>
                <DescriptorName UI="D001835" MajorTopicYN="N">Body Weight</DescriptorName>
                <QualifierName UI="Q000502" MajorTopicYN="Y">physiology</QualifierName>
            </MeshHeading>
            <MeshHeading>
                <DescriptorName UI="D001943" MajorTopicYN="N">Breast Neoplasms</DescriptorName>
                <QualifierName UI="Q000453" MajorTopicYN="Y">epidemiology</QualifierName>
            </MeshHeading>
            <MeshHeading>
                <DescriptorName UI="D015331" MajorTopicYN="N">Cohort Studies</DescriptorName>
            </MeshHeading>
            <MeshHeading>
                <DescriptorName UI="D005260" MajorTopicYN="N">Female</DescriptorName>
            </MeshHeading>
            <MeshHeading>
                <DescriptorName UI="D020249" MajorTopicYN="N">Hormone Replacement Therapy</DescriptorName>
            </MeshHeading>
            <MeshHeading>
                <DescriptorName UI="D006801" MajorTopicYN="N">Humans</DescriptorName>
            </MeshHeading>
            <MeshHeading>
                <DescriptorName UI="D008137" MajorTopicYN="N">Longitudinal Studies</DescriptorName>
            </MeshHeading>
            <MeshHeading>
                <DescriptorName UI="D008875" MajorTopicYN="N">Middle Aged</DescriptorName>
            </MeshHeading>
            <MeshHeading>
                <DescriptorName UI="D009765" MajorTopicYN="N">Obesity</DescriptorName>
                <QualifierName UI="Q000150" MajorTopicYN="N">complications</QualifierName>
            </MeshHeading>
            <MeshHeading>
                <DescriptorName UI="D017698" MajorTopicYN="Y">Postmenopause</DescriptorName>
            </MeshHeading>
            <MeshHeading>
                <DescriptorName UI="D012307" MajorTopicYN="N">Risk Factors</DescriptorName>
            </MeshHeading>
            <MeshHeading>
                <DescriptorName UI="D015430" MajorTopicYN="Y">Weight Gain</DescriptorName>
            </MeshHeading>
        </MeshHeadingList>
    </MedlineCitation>
    <PubmedData>
        <History>
            <PubMedPubDate PubStatus="pubmed">
                <Year>2004</Year>
                <Month>10</Month>
                <Day>1</Day>
                <Hour>5</Hour>
                <Minute>0</Minute>
            </PubMedPubDate>
            <PubMedPubDate PubStatus="medline">
                <Year>2005</Year>
                <Month>4</Month>
                <Day>19</Day>
                <Hour>9</Hour>
                <Minute>0</Minute>
            </PubMedPubDate>
            <PubMedPubDate PubStatus="entrez">
                <Year>2004</Year>
                <Month>10</Month>
                <Day>1</Day>
                <Hour>5</Hour>
                <Minute>0</Minute>
            </PubMedPubDate>
        </History>
        <PublicationStatus>ppublish</PublicationStatus>
        <ArticleIdList>
            <ArticleId IdType="pubmed">15456630</ArticleId>
            <ArticleId IdType="doi">10.1207/s15327914nc4901_2</ArticleId>
        </ArticleIdList>
    </PubmedData>
</PubmedArticle>

</PubmedArticleSet>