<?xml version="1.0" ?>
<!DOCTYPE PubmedArticleSet PUBLIC "-//NLM//DTD PubMedArticle, 1st January 2019//EN" "https://dtd.nlm.nih.gov/ncbi/pubmed/out/pubmed_190101.dtd">
<PubmedArticleSet>
<PubmedArticle>
    <MedlineCitation Status="MEDLINE" Owner="NLM">
        <PMID Version="1">23875907</PMID>
        <DateCompleted>
            <Year>2014</Year>
            <Month>07</Month>
            <Day>28</Day>
        </DateCompleted>
        <DateRevised>
            <Year>2018</Year>
            <Month>11</Month>
            <Day>13</Day>
        </DateRevised>
        <Article PubModel="Print">
            <Journal>
                <ISSN IssnType="Electronic">1540-8167</ISSN>
                <JournalIssue CitedMedium="Internet">
                    <Volume>24</Volume>
                    <Issue>12</Issue>
                    <PubDate>
                        <Year>2013</Year>
                        <Month>Dec</Month>
                    </PubDate>
                </JournalIssue>
                <Title>Journal of cardiovascular electrophysiology</Title>
                <ISOAbbreviation>J. Cardiovasc. Electrophysiol.</ISOAbbreviation>
            </Journal>
            <ArticleTitle>Variable procedural strategies adapted to anatomical characteristics in catheter ablation of the cavotricuspid isthmus using a preoperative multidetector computed tomography analysis.</ArticleTitle>
            <Pagination>
                <MedlinePgn>1344-51</MedlinePgn>
            </Pagination>
            <Abstract>
                <AbstractText Label="OBJECTIVES" NlmCategory="OBJECTIVE">This study aimed to investigate the anatomical characteristics complicating cavotricuspid isthmus (CTI) ablation and the effectiveness of various procedural strategies.</AbstractText>
                <AbstractText Label="METHODS AND RESULTS" NlmCategory="RESULTS">This study included 446 consecutive patients (362 males; mean age 60.5 ± 10.4 years) in whom CTI ablation was performed. A total of 80 consecutive patients were evaluated in a preliminary study. The anatomy of the CTI was evaluated by multidetector row-computed tomography (MDCT) prior to the procedure. A multivariate logistic regression analysis revealed that the angle and mean wall thickness of the CTI, a concave CTI morphology, and a prominent Eustachian ridge, were associated with a difficult CTI ablation (P &lt; 0.01). In the main study, 366 consecutive patients were divided into 2 groups: a modulation group (catheter inversion technique for a concave aspect, prominent Eustachian ridge, and steep angle of the CTI or increased output for a thicker CTI) and nonmodulation group (conventional strategy). The duration and total amount of radiofrequency energy delivered were significantly shorter and smaller in the modulation group than those in the nonmodulation group (162.2 ± 153.5 vs 222.7 ± 191.9 seconds, P &lt; 0.01, and 16,962.4 ± 11,545.6 vs 24,908.5 ± 22,804.2 J, P &lt; 0.01, respectively). The recurrence rate of type 1 atrial flutter after the CTI ablation in the nonmodulation group was significantly higher than that in the modulation group (6.3 vs 1.7%, P = 0.02).</AbstractText>
                <AbstractText Label="CONCLUSION" NlmCategory="CONCLUSIONS">Changing the procedural strategies by adaptating them to the anatomical characteristics improved the outcomes of the CTI ablation.</AbstractText>
            </Abstract>
            <AuthorList CompleteYN="Y">
                <Author ValidYN="Y">
                    <LastName>Kajihara</LastName>
                    <ForeName>Kenta</ForeName>
                    <Initials>K</Initials>
                </Author>
                <Author ValidYN="Y">
                    <LastName>Nakano</LastName>
                    <ForeName>Yukiko</ForeName>
                    <Initials>Y</Initials>
                </Author>
                <Author ValidYN="Y">
                    <LastName>Hirai</LastName>
                    <ForeName>Yukoh</ForeName>
                    <Initials>Y</Initials>
                </Author>
                <Author ValidYN="Y">
                    <LastName>Ogi</LastName>
                    <ForeName>Hiroshi</ForeName>
                    <Initials>H</Initials>
                </Author>
                <Author ValidYN="Y">
                    <LastName>Oda</LastName>
                    <ForeName>Noboru</ForeName>
                    <Initials>N</Initials>
                </Author>
                <Author ValidYN="Y">
                    <LastName>Suenari</LastName>
                    <ForeName>Kazuyoshi</ForeName>
                    <Initials>K</Initials>
                </Author>
                <Author ValidYN="Y">
                    <LastName>Makita</LastName>
                    <ForeName>Yuko</ForeName>
                    <Initials>Y</Initials>
                </Author>
                <Author ValidYN="Y">
                    <LastName>Sairaku</LastName>
                    <ForeName>Akinori</ForeName>
                    <Initials>A</Initials>
                </Author>
                <Author ValidYN="Y">
                    <LastName>Tokuyama</LastName>
                    <ForeName>Takehito</ForeName>
                    <Initials>T</Initials>
                </Author>
                <Author ValidYN="Y">
                    <LastName>Motoda</LastName>
                    <ForeName>Chikaaki</ForeName>
                    <Initials>C</Initials>
                </Author>
                <Author ValidYN="Y">
                    <LastName>Fujiwara</LastName>
                    <ForeName>Mai</ForeName>
                    <Initials>M</Initials>
                </Author>
                <Author ValidYN="Y">
                    <LastName>Watanabe</LastName>
                    <ForeName>Yoshikazu</ForeName>
                    <Initials>Y</Initials>
                </Author>
                <Author ValidYN="Y">
                    <LastName>Kiguchi</LastName>
                    <ForeName>Masao</ForeName>
                    <Initials>M</Initials>
                </Author>
                <Author ValidYN="Y">
                    <LastName>Kihara</LastName>
                    <ForeName>Yasuki</ForeName>
                    <Initials>Y</Initials>
                </Author>
            </AuthorList>
            <Language>eng</Language>
            <PublicationTypeList>
                <PublicationType UI="D016428">Journal Article</PublicationType>
                <PublicationType UI="D016449">Randomized Controlled Trial</PublicationType>
            </PublicationTypeList>
        </Article>
        <MedlineJournalInfo>
            <Country>United States</Country>
            <MedlineTA>J Cardiovasc Electrophysiol</MedlineTA>
            <NlmUniqueID>9010756</NlmUniqueID>
            <ISSNLinking>1045-3873</ISSNLinking>
        </MedlineJournalInfo>
        <CitationSubset>IM</CitationSubset>
        <CommentsCorrectionsList>
            <CommentsCorrections RefType="CommentIn">
                <RefSource>J Cardiovasc Electrophysiol. 2013 Dec;24(12):1352-3</RefSource>
                <PMID Version="1">24102875</PMID>
            </CommentsCorrections>
        </CommentsCorrectionsList>
        <MeshHeadingList>
            <MeshHeading>
                <DescriptorName UI="D000368" MajorTopicYN="N">Aged</DescriptorName>
            </MeshHeading>
            <MeshHeading>
                <DescriptorName UI="D001282" MajorTopicYN="N">Atrial Flutter</DescriptorName>
                <QualifierName UI="Q000000981" MajorTopicYN="Y">diagnostic imaging</QualifierName>
                <QualifierName UI="Q000503" MajorTopicYN="N">physiopathology</QualifierName>
                <QualifierName UI="Q000601" MajorTopicYN="Y">surgery</QualifierName>
            </MeshHeading>
            <MeshHeading>
                <DescriptorName UI="D017115" MajorTopicYN="Y">Catheter Ablation</DescriptorName>
                <QualifierName UI="Q000009" MajorTopicYN="N">adverse effects</QualifierName>
            </MeshHeading>
            <MeshHeading>
                <DescriptorName UI="D022062" MajorTopicYN="N">Electrophysiologic Techniques, Cardiac</DescriptorName>
            </MeshHeading>
            <MeshHeading>
                <DescriptorName UI="D005260" MajorTopicYN="N">Female</DescriptorName>
            </MeshHeading>
            <MeshHeading>
                <DescriptorName UI="D006325" MajorTopicYN="N">Heart Atria</DescriptorName>
                <QualifierName UI="Q000000981" MajorTopicYN="N">diagnostic imaging</QualifierName>
                <QualifierName UI="Q000503" MajorTopicYN="N">physiopathology</QualifierName>
                <QualifierName UI="Q000601" MajorTopicYN="N">surgery</QualifierName>
            </MeshHeading>
            <MeshHeading>
                <DescriptorName UI="D006801" MajorTopicYN="N">Humans</DescriptorName>
            </MeshHeading>
            <MeshHeading>
                <DescriptorName UI="D007564" MajorTopicYN="N">Japan</DescriptorName>
            </MeshHeading>
            <MeshHeading>
                <DescriptorName UI="D016015" MajorTopicYN="N">Logistic Models</DescriptorName>
            </MeshHeading>
            <MeshHeading>
                <DescriptorName UI="D008297" MajorTopicYN="N">Male</DescriptorName>
            </MeshHeading>
            <MeshHeading>
                <DescriptorName UI="D008875" MajorTopicYN="N">Middle Aged</DescriptorName>
            </MeshHeading>
            <MeshHeading>
                <DescriptorName UI="D061330" MajorTopicYN="Y">Multidetector Computed Tomography</DescriptorName>
            </MeshHeading>
            <MeshHeading>
                <DescriptorName UI="D015999" MajorTopicYN="N">Multivariate Analysis</DescriptorName>
            </MeshHeading>
            <MeshHeading>
                <DescriptorName UI="D011237" MajorTopicYN="N">Predictive Value of Tests</DescriptorName>
            </MeshHeading>
            <MeshHeading>
                <DescriptorName UI="D011300" MajorTopicYN="N">Preoperative Care</DescriptorName>
            </MeshHeading>
            <MeshHeading>
                <DescriptorName UI="D011446" MajorTopicYN="N">Prospective Studies</DescriptorName>
            </MeshHeading>
            <MeshHeading>
                <DescriptorName UI="D012008" MajorTopicYN="N">Recurrence</DescriptorName>
            </MeshHeading>
            <MeshHeading>
                <DescriptorName UI="D012307" MajorTopicYN="N">Risk Factors</DescriptorName>
            </MeshHeading>
            <MeshHeading>
                <DescriptorName UI="D013997" MajorTopicYN="N">Time Factors</DescriptorName>
            </MeshHeading>
            <MeshHeading>
                <DescriptorName UI="D016896" MajorTopicYN="N">Treatment Outcome</DescriptorName>
            </MeshHeading>
        </MeshHeadingList>
    </MedlineCitation>
    <PubmedData>
        <History>
            <PubMedPubDate PubStatus="received">
                <Year>2013</Year>
                <Month>04</Month>
                <Day>20</Day>
            </PubMedPubDate>
            <PubMedPubDate PubStatus="revised">
                <Year>2013</Year>
                <Month>06</Month>
                <Day>14</Day>
            </PubMedPubDate>
            <PubMedPubDate PubStatus="accepted">
                <Year>2013</Year>
                <Month>06</Month>
                <Day>26</Day>
            </PubMedPubDate>
            <PubMedPubDate PubStatus="entrez">
                <Year>2013</Year>
                <Month>7</Month>
                <Day>24</Day>
                <Hour>6</Hour>
                <Minute>0</Minute>
            </PubMedPubDate>
            <PubMedPubDate PubStatus="pubmed">
                <Year>2013</Year>
                <Month>7</Month>
                <Day>24</Day>
                <Hour>6</Hour>
                <Minute>0</Minute>
            </PubMedPubDate>
            <PubMedPubDate PubStatus="medline">
                <Year>2014</Year>
                <Month>7</Month>
                <Day>30</Day>
                <Hour>6</Hour>
                <Minute>0</Minute>
            </PubMedPubDate>
        </History>
        <PublicationStatus>ppublish</PublicationStatus>
        <ArticleIdList>
            <ArticleId IdType="pubmed">23875907</ArticleId>
            <ArticleId IdType="doi">10.1111/jce.12231</ArticleId>
            <ArticleId IdType="pmc">PMC4229059</ArticleId>
        </ArticleIdList>
        <ReferenceList>
            <Reference>
                <Citation>Circulation. 1999 Apr 6;99(13):1700-5</Citation>
                <ArticleIdList>
                    <ArticleId IdType="pubmed">10190879</ArticleId>
                </ArticleIdList>
            </Reference>
            <Reference>
                <Citation>J Cardiovasc Electrophysiol. 1999 May;10(5):662-9</Citation>
                <ArticleIdList>
                    <ArticleId IdType="pubmed">10355922</ArticleId>
                </ArticleIdList>
            </Reference>
            <Reference>
                <Citation>Circulation. 1999 Feb 2;99(4):534-40</Citation>
                <ArticleIdList>
                    <ArticleId IdType="pubmed">9927400</ArticleId>
                </ArticleIdList>
            </Reference>
            <Reference>
                <Citation>Pacing Clin Electrophysiol. 1998 Feb;21(2):401-9</Citation>
                <ArticleIdList>
                    <ArticleId IdType="pubmed">9507541</ArticleId>
                </ArticleIdList>
            </Reference>
            <Reference>
                <Citation>Circulation. 1996 Dec 15;94(12):3204-13</Citation>
                <ArticleIdList>
                    <ArticleId IdType="pubmed">8989130</ArticleId>
                </ArticleIdList>
            </Reference>
            <Reference>
                <Citation>Circulation. 1995 Sep 15;92(6):1389-92</Citation>
                <ArticleIdList>
                    <ArticleId IdType="pubmed">7664417</ArticleId>
                </ArticleIdList>
            </Reference>
            <Reference>
                <Citation>Circulation. 1994 Dec;90(6):2804-14</Citation>
                <ArticleIdList>
                    <ArticleId IdType="pubmed">7994824</ArticleId>
                </ArticleIdList>
            </Reference>
            <Reference>
                <Citation>Am J Cardiol. 1993 Mar 15;71(8):705-9</Citation>
                <ArticleIdList>
                    <ArticleId IdType="pubmed">8447269</ArticleId>
                </ArticleIdList>
            </Reference>
            <Reference>
                <Citation>Europace. 2004 Sep;6(5):407-17</Citation>
                <ArticleIdList>
                    <ArticleId IdType="pubmed">15294265</ArticleId>
                </ArticleIdList>
            </Reference>
            <Reference>
                <Citation>Pacing Clin Electrophysiol. 2004 Jun;27(6 Pt 1):775-8</Citation>
                <ArticleIdList>
                    <ArticleId IdType="pubmed">15189533</ArticleId>
                </ArticleIdList>
            </Reference>
            <Reference>
                <Citation>Eur Heart J. 2004 Jun;25(11):963-9</Citation>
                <ArticleIdList>
                    <ArticleId IdType="pubmed">15172468</ArticleId>
                </ArticleIdList>
            </Reference>
            <Reference>
                <Citation>J Interv Card Electrophysiol. 2002 Aug;7(1):77-82</Citation>
                <ArticleIdList>
                    <ArticleId IdType="pubmed">12391423</ArticleId>
                </ArticleIdList>
            </Reference>
            <Reference>
                <Citation>Circulation. 2000 May 9;101(18):2178-84</Citation>
                <ArticleIdList>
                    <ArticleId IdType="pubmed">10801759</ArticleId>
                </ArticleIdList>
            </Reference>
            <Reference>
                <Citation>J Am Coll Cardiol. 1999 Jan;33(1):39-45</Citation>
                <ArticleIdList>
                    <ArticleId IdType="pubmed">9935006</ArticleId>
                </ArticleIdList>
            </Reference>
            <Reference>
                <Citation>J Cardiovasc Electrophysiol. 2012 Jun;23(6):672-6</Citation>
                <ArticleIdList>
                    <ArticleId IdType="pubmed">22554221</ArticleId>
                </ArticleIdList>
            </Reference>
            <Reference>
                <Citation>J Cardiovasc Electrophysiol. 2012 May;23(5):479-85</Citation>
                <ArticleIdList>
                    <ArticleId IdType="pubmed">22458432</ArticleId>
                </ArticleIdList>
            </Reference>
            <Reference>
                <Citation>Europace. 2010 Mar;12(3):402-9</Citation>
                <ArticleIdList>
                    <ArticleId IdType="pubmed">20083483</ArticleId>
                </ArticleIdList>
            </Reference>
            <Reference>
                <Citation>Radiology. 2008 Jun;247(3):658-68</Citation>
                <ArticleIdList>
                    <ArticleId IdType="pubmed">18487534</ArticleId>
                </ArticleIdList>
            </Reference>
            <Reference>
                <Citation>Am Heart J. 2007 Dec;154(6):1191-8</Citation>
                <ArticleIdList>
                    <ArticleId IdType="pubmed">18035094</ArticleId>
                </ArticleIdList>
            </Reference>
            <Reference>
                <Citation>J Interv Card Electrophysiol. 2007 Nov;20(1-2):29-35</Citation>
                <ArticleIdList>
                    <ArticleId IdType="pubmed">17943430</ArticleId>
                </ArticleIdList>
            </Reference>
            <Reference>
                <Citation>J Cardiovasc Electrophysiol. 2007 Jan;18(1):18-22</Citation>
                <ArticleIdList>
                    <ArticleId IdType="pubmed">17081213</ArticleId>
                </ArticleIdList>
            </Reference>
            <Reference>
                <Citation>Eur Heart J. 2006 Aug;27(15):1833-40</Citation>
                <ArticleIdList>
                    <ArticleId IdType="pubmed">16807277</ArticleId>
                </ArticleIdList>
            </Reference>
            <Reference>
                <Citation>Z Kardiol. 2005 Oct;94(10):674-8</Citation>
                <ArticleIdList>
                    <ArticleId IdType="pubmed">16200482</ArticleId>
                </ArticleIdList>
            </Reference>
            <Reference>
                <Citation>Pacing Clin Electrophysiol. 2005 Aug;28(8):808-18</Citation>
                <ArticleIdList>
                    <ArticleId IdType="pubmed">16105009</ArticleId>
                </ArticleIdList>
            </Reference>
        </ReferenceList>
    </PubmedData>
</PubmedArticle>

</PubmedArticleSet>