<?xml version="1.0" ?>
<!DOCTYPE PubmedArticleSet PUBLIC "-//NLM//DTD PubMedArticle, 1st January 2019//EN" "https://dtd.nlm.nih.gov/ncbi/pubmed/out/pubmed_190101.dtd">
<PubmedArticleSet>
<PubmedArticle>
    <MedlineCitation Status="MEDLINE" Owner="NLM">
        <PMID Version="1">6585942</PMID>
        <DateCompleted>
            <Year>1984</Year>
            <Month>06</Month>
            <Day>19</Day>
        </DateCompleted>
        <DateRevised>
            <Year>2004</Year>
            <Month>11</Month>
            <Day>17</Day>
        </DateRevised>
        <Article PubModel="Print">
            <Journal>
                <ISSN IssnType="Print">0346-8720</ISSN>
                <JournalIssue CitedMedium="Print">
                    <Volume>9</Volume>
                    <PubDate>
                        <Year>1983</Year>
                    </PubDate>
                </JournalIssue>
                <Title>Scandinavian journal of rehabilitation medicine. Supplement</Title>
                <ISOAbbreviation>Scand J Rehabil Med Suppl</ISOAbbreviation>
            </Journal>
            <ArticleTitle>Exercise training of patients with intermittent claudication.</ArticleTitle>
            <Pagination>
                <MedlinePgn>20-6</MedlinePgn>
            </Pagination>
            <AuthorList CompleteYN="Y">
                <Author ValidYN="Y">
                    <LastName>Dahllöf</LastName>
                    <ForeName>A G</ForeName>
                    <Initials>AG</Initials>
                </Author>
                <Author ValidYN="Y">
                    <LastName>Holm</LastName>
                    <ForeName>J</ForeName>
                    <Initials>J</Initials>
                </Author>
                <Author ValidYN="Y">
                    <LastName>Scherstén</LastName>
                    <ForeName>T</ForeName>
                    <Initials>T</Initials>
                </Author>
            </AuthorList>
            <Language>eng</Language>
            <PublicationTypeList>
                <PublicationType UI="D016428">Journal Article</PublicationType>
            </PublicationTypeList>
        </Article>
        <MedlineJournalInfo>
            <Country>Sweden</Country>
            <MedlineTA>Scand J Rehabil Med Suppl</MedlineTA>
            <NlmUniqueID>0254404</NlmUniqueID>
            <ISSNLinking>0346-8720</ISSNLinking>
        </MedlineJournalInfo>
        <CitationSubset>IM</CitationSubset>
        <MeshHeadingList>
            <MeshHeading>
                <DescriptorName UI="D005081" MajorTopicYN="Y">Exercise Therapy</DescriptorName>
            </MeshHeading>
            <MeshHeading>
                <DescriptorName UI="D006801" MajorTopicYN="N">Humans</DescriptorName>
            </MeshHeading>
            <MeshHeading>
                <DescriptorName UI="D007383" MajorTopicYN="N">Intermittent Claudication</DescriptorName>
                <QualifierName UI="Q000378" MajorTopicYN="N">metabolism</QualifierName>
                <QualifierName UI="Q000628" MajorTopicYN="Y">therapy</QualifierName>
            </MeshHeading>
            <MeshHeading>
                <DescriptorName UI="D010806" MajorTopicYN="Y">Physical Education and Training</DescriptorName>
            </MeshHeading>
        </MeshHeadingList>
    </MedlineCitation>
    <PubmedData>
        <History>
            <PubMedPubDate PubStatus="pubmed">
                <Year>1983</Year>
                <Month>1</Month>
                <Day>1</Day>
            </PubMedPubDate>
            <PubMedPubDate PubStatus="medline">
                <Year>1983</Year>
                <Month>1</Month>
                <Day>1</Day>
                <Hour>0</Hour>
                <Minute>1</Minute>
            </PubMedPubDate>
            <PubMedPubDate PubStatus="entrez">
                <Year>1983</Year>
                <Month>1</Month>
                <Day>1</Day>
                <Hour>0</Hour>
                <Minute>0</Minute>
            </PubMedPubDate>
        </History>
        <PublicationStatus>ppublish</PublicationStatus>
        <ArticleIdList>
            <ArticleId IdType="pubmed">6585942</ArticleId>
        </ArticleIdList>
    </PubmedData>
</PubmedArticle>

</PubmedArticleSet>