<?xml version="1.0" ?>
<!DOCTYPE PubmedArticleSet PUBLIC "-//NLM//DTD PubMedArticle, 1st January 2019//EN" "https://dtd.nlm.nih.gov/ncbi/pubmed/out/pubmed_190101.dtd">
<PubmedArticleSet>
<PubmedArticle>
    <MedlineCitation Status="PubMed-not-MEDLINE" Owner="NLM">
        <PMID Version="1">12105897</PMID>
        <DateCompleted>
            <Year>2002</Year>
            <Month>09</Month>
            <Day>18</Day>
        </DateCompleted>
        <DateRevised>
            <Year>2019</Year>
            <Month>07</Month>
            <Day>08</Day>
        </DateRevised>
        <Article PubModel="Print">
            <Journal>
                <ISSN IssnType="Print">0002-7863</ISSN>
                <JournalIssue CitedMedium="Print">
                    <Volume>124</Volume>
                    <Issue>28</Issue>
                    <PubDate>
                        <Year>2002</Year>
                        <Month>Jul</Month>
                        <Day>17</Day>
                    </PubDate>
                </JournalIssue>
                <Title>Journal of the American Chemical Society</Title>
                <ISOAbbreviation>J Am Chem Soc</ISOAbbreviation>
            </Journal>
            <ArticleTitle>Size-controlled synthesis of magnetite nanoparticles.</ArticleTitle>
            <Pagination>
                <MedlinePgn>8204-5</MedlinePgn>
            </Pagination>
            <Abstract>
                <AbstractText>Monodisperse magnetite nanoparticles have been synthesized by high-temperature solution-phase reaction of Fe(acac)3 in phenyl ether with alcohol, oleic acid, and oleylamine. Seed-mediated growth is used to control Fe3O4 nanoparticle size, and variously sized nanoparticles from 3 to 20 nm have been produced. The as-synthesized Fe3O4 nanoparticles have inverse spinel structure, and their assemblies can be transformed into gamma-Fe2O3 or alpha-Fe nanoparticle assemblies, depending on the annealing conditions. The reported procedure can be used as a general approach to various ferrite nanoparticles and nanoparticle superlattices.</AbstractText>
            </Abstract>
            <AuthorList CompleteYN="Y">
                <Author ValidYN="Y">
                    <LastName>Sun</LastName>
                    <ForeName>Shouheng</ForeName>
                    <Initials>S</Initials>
                    <AffiliationInfo>
                        <Affiliation>IBM T. J. Watson Research Center, Yorktown Heights, New York 10598, USA. ssun@us.ibm.com</Affiliation>
                    </AffiliationInfo>
                </Author>
                <Author ValidYN="Y">
                    <LastName>Zeng</LastName>
                    <ForeName>Hao</ForeName>
                    <Initials>H</Initials>
                </Author>
            </AuthorList>
            <Language>eng</Language>
            <PublicationTypeList>
                <PublicationType UI="D016428">Journal Article</PublicationType>
            </PublicationTypeList>
        </Article>
        <MedlineJournalInfo>
            <Country>United States</Country>
            <MedlineTA>J Am Chem Soc</MedlineTA>
            <NlmUniqueID>7503056</NlmUniqueID>
            <ISSNLinking>0002-7863</ISSNLinking>
        </MedlineJournalInfo>
    </MedlineCitation>
    <PubmedData>
        <History>
            <PubMedPubDate PubStatus="pubmed">
                <Year>2002</Year>
                <Month>7</Month>
                <Day>11</Day>
                <Hour>10</Hour>
                <Minute>0</Minute>
            </PubMedPubDate>
            <PubMedPubDate PubStatus="medline">
                <Year>2002</Year>
                <Month>7</Month>
                <Day>11</Day>
                <Hour>10</Hour>
                <Minute>1</Minute>
            </PubMedPubDate>
            <PubMedPubDate PubStatus="entrez">
                <Year>2002</Year>
                <Month>7</Month>
                <Day>11</Day>
                <Hour>10</Hour>
                <Minute>0</Minute>
            </PubMedPubDate>
        </History>
        <PublicationStatus>ppublish</PublicationStatus>
        <ArticleIdList>
            <ArticleId IdType="pubmed">12105897</ArticleId>
            <ArticleId IdType="pii">ja026501x</ArticleId>
            <ArticleId IdType="doi">10.1021/ja026501x</ArticleId>
        </ArticleIdList>
    </PubmedData>
</PubmedArticle>

</PubmedArticleSet>
