<?xml version="1.0" ?>
<!DOCTYPE PubmedArticleSet PUBLIC "-//NLM//DTD PubMedArticle, 1st January 2019//EN" "https://dtd.nlm.nih.gov/ncbi/pubmed/out/pubmed_190101.dtd">
<PubmedArticleSet>
<PubmedArticle>
    <MedlineCitation Status="PubMed-not-MEDLINE" Owner="NLM">
        <PMID Version="1">16303525</PMID>
        <DateCompleted>
            <Year>2006</Year>
            <Month>01</Month>
            <Day>09</Day>
        </DateCompleted>
        <DateRevised>
            <Year>2005</Year>
            <Month>11</Month>
            <Day>23</Day>
        </DateRevised>
        <Article PubModel="Print">
            <Journal>
                <ISSN IssnType="Print">1367-0484</ISSN>
                <JournalIssue CitedMedium="Print">
                    <Volume>27</Volume>
                    <Issue>1</Issue>
                    <PubDate>
                        <Year>2004</Year>
                        <Month>Mar</Month>
                    </PubDate>
                </JournalIssue>
                <Title>Contact lens &amp; anterior eye : the journal of the British Contact Lens Association</Title>
                <ISOAbbreviation>Cont Lens Anterior Eye</ISOAbbreviation>
            </Journal>
            <ArticleTitle>Non-contact tonometry over soft contact lenses: effect of contact lens power on the measurement of intra-ocular pressure.</ArticleTitle>
            <Pagination>
                <MedlinePgn>33-7</MedlinePgn>
            </Pagination>
            <Abstract>
                <AbstractText Label="PURPOSE" NlmCategory="OBJECTIVE">To perform non-contact applanation tonometry over soft contact lenses and to examine any differences between the measured IOPs with and without the contact lens.</AbstractText>
                <AbstractText Label="METHOD" NlmCategory="METHODS">IOP was measured at one eye of eight subjects and re-evaluated through a soft lens in situ over the cornea. Seventy percent (ES70, Lunelle) water contact lenses or powers ranging from -15.00 D to +13.00 D were used.</AbstractText>
                <AbstractText Label="RESULTS" NlmCategory="RESULTS">Mean IOP without lenses was 15.2 mmHg (S.D. = +/-4.2) and this did not change significantly for lenses ranging from -15.00 D to +3.00 D (P &gt; 0.01) but did change for lens powers +6.00 D and above (P&lt;0.01). The least squares line describing the change in measured IOP (deltaIOP) as a function of lens power (x) has the following characteristics, deltaIOP = 0.022 + 0.591x + 0.11x2 + 0.005x3 (r = 0.985, P = 0.0001).</AbstractText>
                <AbstractText Label="CONCLUSION" NlmCategory="CONCLUSIONS">Non-contact tonometry can be performed with sufficient accuracy over a soft lens on condition: (a) lens centre thickness is no more 0.30 mm and (b) power is not greater than +3D.</AbstractText>
            </Abstract>
            <AuthorList CompleteYN="Y">
                <Author ValidYN="Y">
                    <LastName>Patel</LastName>
                    <ForeName>S</ForeName>
                    <Initials>S</Initials>
                    <AffiliationInfo>
                        <Affiliation>Common Services Agency, Edinburgh, United Kingdom and Instituto Oftalmologico de Alicante, University Miguel Hernandez, Alicante, Spain. sudhir.patel@psd.csa.scot.nhs.uk</Affiliation>
                    </AffiliationInfo>
                </Author>
                <Author ValidYN="Y">
                    <LastName>Illahi</LastName>
                    <ForeName>W</ForeName>
                    <Initials>W</Initials>
                </Author>
            </AuthorList>
            <Language>eng</Language>
            <PublicationTypeList>
                <PublicationType UI="D016428">Journal Article</PublicationType>
            </PublicationTypeList>
        </Article>
        <MedlineJournalInfo>
            <Country>England</Country>
            <MedlineTA>Cont Lens Anterior Eye</MedlineTA>
            <NlmUniqueID>9712714</NlmUniqueID>
            <ISSNLinking>1367-0484</ISSNLinking>
        </MedlineJournalInfo>
    </MedlineCitation>
    <PubmedData>
        <History>
            <PubMedPubDate PubStatus="pubmed">
                <Year>2005</Year>
                <Month>11</Month>
                <Day>24</Day>
                <Hour>9</Hour>
                <Minute>0</Minute>
            </PubMedPubDate>
            <PubMedPubDate PubStatus="medline">
                <Year>2005</Year>
                <Month>11</Month>
                <Day>24</Day>
                <Hour>9</Hour>
                <Minute>1</Minute>
            </PubMedPubDate>
            <PubMedPubDate PubStatus="entrez">
                <Year>2005</Year>
                <Month>11</Month>
                <Day>24</Day>
                <Hour>9</Hour>
                <Minute>0</Minute>
            </PubMedPubDate>
        </History>
        <PublicationStatus>ppublish</PublicationStatus>
        <ArticleIdList>
            <ArticleId IdType="pubmed">16303525</ArticleId>
            <ArticleId IdType="pii">S1367-0484(03)00085-7</ArticleId>
            <ArticleId IdType="doi">10.1016/j.clae.2003.10.002</ArticleId>
        </ArticleIdList>
    </PubmedData>
</PubmedArticle>

</PubmedArticleSet>
