<?xml version="1.0" ?>
<!DOCTYPE PubmedArticleSet PUBLIC "-//NLM//DTD PubMedArticle, 1st January 2019//EN" "https://dtd.nlm.nih.gov/ncbi/pubmed/out/pubmed_190101.dtd">
<PubmedArticleSet>
<PubmedArticle>
    <MedlineCitation Status="MEDLINE" Owner="NLM">
        <PMID Version="1">24802054</PMID>
        <DateCompleted>
            <Year>2015</Year>
            <Month>01</Month>
            <Day>12</Day>
        </DateCompleted>
        <DateRevised>
            <Year>2014</Year>
            <Month>05</Month>
            <Day>30</Day>
        </DateRevised>
        <Article PubModel="Print-Electronic">
            <Journal>
                <ISSN IssnType="Electronic">1873-3379</ISSN>
                <JournalIssue CitedMedium="Internet">
                    <Volume>35</Volume>
                    <Issue>8</Issue>
                    <PubDate>
                        <Year>2014</Year>
                        <Month>Aug</Month>
                    </PubDate>
                </JournalIssue>
                <Title>Research in developmental disabilities</Title>
                <ISOAbbreviation>Res Dev Disabil</ISOAbbreviation>
            </Journal>
            <ArticleTitle>The written language performance of children with Attention Deficit Hyperactivity Disorder in Taiwan.</ArticleTitle>
            <Pagination>
                <MedlinePgn>1878-84</MedlinePgn>
            </Pagination>
            <ELocationID EIdType="doi" ValidYN="Y">10.1016/j.ridd.2014.04.006</ELocationID>
            <ELocationID EIdType="pii" ValidYN="Y">S0891-4222(14)00155-3</ELocationID>
            <Abstract>
                <AbstractText>Poor writing is common in children with Attention Deficit Hyperactivity Disorder (ADHD). However, the writing performance of children with ADHD has been rarely formally explored in Taiwan, so the purpose of this study was to investigate writing features of children with ADHD in Taiwan. There were 25 children with ADHD and 25 normal children involved in a standardization writing assessment - Written Language Test for Children, to assess their performance at the dictation, sentence combination, adding/deducting redical, cloze and sentence making subtests. The results showed that except for the score of the sentence combining subtest, the score of children with ADHD was lower than the normal student in the rest of the subtests. Almost 60% of ADHD children's scores were below the 25th percentile numbers, but only 20% for normal children. Thus, writing problems were common for children with ADHD in Taiwan, too. First, children with ADHD performed worse than normal children on the dictation and cloze subtests, showing the weaker abilities of retrieving correct characters from their mental lexicon. Second, children with ADHD performed worse on the adding/deducting redical subtest than normal children did. Finally, at the language level, the score of children with ADHD on the sentence combination subtest was not lower than normal children, implicating their normal grammatic competence. It is worth mentioning that Taiwanese children with ADHD ignore the details of characters when they are writing, a finding that is common across languages.</AbstractText>
                <CopyrightInformation>Copyright © 2014 Elsevier Ltd. All rights reserved.</CopyrightInformation>
            </Abstract>
            <AuthorList CompleteYN="Y">
                <Author ValidYN="Y">
                    <LastName>Lee</LastName>
                    <ForeName>Hom-Yi</ForeName>
                    <Initials>HY</Initials>
                    <AffiliationInfo>
                        <Affiliation>Department of Psychology, Chung Shan Medical University, Taichung, Taiwan; Department of Clinical Psychology, Chung Shan Medical University Hospital, Taichung, Taiwan. Electronic address: hoyih@csmu.edu.tw.</Affiliation>
                    </AffiliationInfo>
                </Author>
                <Author ValidYN="Y">
                    <LastName>Chen</LastName>
                    <ForeName>Rou-An</ForeName>
                    <Initials>RA</Initials>
                    <AffiliationInfo>
                        <Affiliation>Department of Psychology, Chung Shan Medical University, Taichung, Taiwan.</Affiliation>
                    </AffiliationInfo>
                </Author>
                <Author ValidYN="Y">
                    <LastName>Lin</LastName>
                    <ForeName>Yu-Shiuan</ForeName>
                    <Initials>YS</Initials>
                    <AffiliationInfo>
                        <Affiliation>Department of Psychology, Chung Shan Medical University, Taichung, Taiwan.</Affiliation>
                    </AffiliationInfo>
                </Author>
                <Author ValidYN="Y">
                    <LastName>Yang</LastName>
                    <ForeName>Yu-Chi</ForeName>
                    <Initials>YC</Initials>
                    <AffiliationInfo>
                        <Affiliation>Department of Psychology, Chung Shan Medical University, Taichung, Taiwan.</Affiliation>
                    </AffiliationInfo>
                </Author>
                <Author ValidYN="Y">
                    <LastName>Huang</LastName>
                    <ForeName>Chiung-Wei</ForeName>
                    <Initials>CW</Initials>
                    <AffiliationInfo>
                        <Affiliation>Department of Psychology, Chung Shan Medical University, Taichung, Taiwan.</Affiliation>
                    </AffiliationInfo>
                </Author>
                <Author ValidYN="Y">
                    <LastName>Chen</LastName>
                    <ForeName>Sz-Chi</ForeName>
                    <Initials>SC</Initials>
                    <AffiliationInfo>
                        <Affiliation>Department of Psychology, Chung Shan Medical University, Taichung, Taiwan.</Affiliation>
                    </AffiliationInfo>
                </Author>
            </AuthorList>
            <Language>eng</Language>
            <PublicationTypeList>
                <PublicationType UI="D016428">Journal Article</PublicationType>
            </PublicationTypeList>
            <ArticleDate DateType="Electronic">
                <Year>2014</Year>
                <Month>05</Month>
                <Day>05</Day>
            </ArticleDate>
        </Article>
        <MedlineJournalInfo>
            <Country>United States</Country>
            <MedlineTA>Res Dev Disabil</MedlineTA>
            <NlmUniqueID>8709782</NlmUniqueID>
            <ISSNLinking>0891-4222</ISSNLinking>
        </MedlineJournalInfo>
        <CitationSubset>IM</CitationSubset>
        <MeshHeadingList>
            <MeshHeading>
                <DescriptorName UI="D044466" MajorTopicYN="N">Asian Continental Ancestry Group</DescriptorName>
                <QualifierName UI="Q000523" MajorTopicYN="N">psychology</QualifierName>
            </MeshHeading>
            <MeshHeading>
                <DescriptorName UI="D001289" MajorTopicYN="N">Attention Deficit Disorder with Hyperactivity</DescriptorName>
                <QualifierName UI="Q000523" MajorTopicYN="Y">psychology</QualifierName>
                <QualifierName UI="Q000534" MajorTopicYN="N">rehabilitation</QualifierName>
            </MeshHeading>
            <MeshHeading>
                <DescriptorName UI="D002648" MajorTopicYN="N">Child</DescriptorName>
            </MeshHeading>
            <MeshHeading>
                <DescriptorName UI="D005260" MajorTopicYN="N">Female</DescriptorName>
            </MeshHeading>
            <MeshHeading>
                <DescriptorName UI="D006236" MajorTopicYN="Y">Handwriting</DescriptorName>
            </MeshHeading>
            <MeshHeading>
                <DescriptorName UI="D006801" MajorTopicYN="N">Humans</DescriptorName>
            </MeshHeading>
            <MeshHeading>
                <DescriptorName UI="D007175" MajorTopicYN="N">Impulsive Behavior</DescriptorName>
            </MeshHeading>
            <MeshHeading>
                <DescriptorName UI="D007805" MajorTopicYN="N">Language Development Disorders</DescriptorName>
                <QualifierName UI="Q000523" MajorTopicYN="N">psychology</QualifierName>
                <QualifierName UI="Q000534" MajorTopicYN="N">rehabilitation</QualifierName>
            </MeshHeading>
            <MeshHeading>
                <DescriptorName UI="D008297" MajorTopicYN="N">Male</DescriptorName>
            </MeshHeading>
            <MeshHeading>
                <DescriptorName UI="D009042" MajorTopicYN="N">Motivation</DescriptorName>
            </MeshHeading>
            <MeshHeading>
                <DescriptorName UI="D011597" MajorTopicYN="N">Psychomotor Performance</DescriptorName>
            </MeshHeading>
            <MeshHeading>
                <DescriptorName UI="D011932" MajorTopicYN="Y">Reading</DescriptorName>
            </MeshHeading>
            <MeshHeading>
                <DescriptorName UI="D012660" MajorTopicYN="Y">Semantics</DescriptorName>
            </MeshHeading>
            <MeshHeading>
                <DescriptorName UI="D013624" MajorTopicYN="N" Type="Geographic">Taiwan</DescriptorName>
            </MeshHeading>
            <MeshHeading>
                <DescriptorName UI="D014888" MajorTopicYN="N">Wechsler Scales</DescriptorName>
            </MeshHeading>
            <MeshHeading>
                <DescriptorName UI="D014956" MajorTopicYN="Y">Writing</DescriptorName>
            </MeshHeading>
        </MeshHeadingList>
        <KeywordList Owner="NOTNLM">
            <Keyword MajorTopicYN="N">Character representation</Keyword>
            <Keyword MajorTopicYN="N">Handwriting</Keyword>
            <Keyword MajorTopicYN="N">Lexical–semantic</Keyword>
            <Keyword MajorTopicYN="N">Sentence making</Keyword>
        </KeywordList>
    </MedlineCitation>
    <PubmedData>
        <History>
            <PubMedPubDate PubStatus="received">
                <Year>2013</Year>
                <Month>12</Month>
                <Day>20</Day>
            </PubMedPubDate>
            <PubMedPubDate PubStatus="revised">
                <Year>2014</Year>
                <Month>03</Month>
                <Day>30</Day>
            </PubMedPubDate>
            <PubMedPubDate PubStatus="accepted">
                <Year>2014</Year>
                <Month>04</Month>
                <Day>01</Day>
            </PubMedPubDate>
            <PubMedPubDate PubStatus="entrez">
                <Year>2014</Year>
                <Month>5</Month>
                <Day>8</Day>
                <Hour>6</Hour>
                <Minute>0</Minute>
            </PubMedPubDate>
            <PubMedPubDate PubStatus="pubmed">
                <Year>2014</Year>
                <Month>5</Month>
                <Day>8</Day>
                <Hour>6</Hour>
                <Minute>0</Minute>
            </PubMedPubDate>
            <PubMedPubDate PubStatus="medline">
                <Year>2015</Year>
                <Month>1</Month>
                <Day>13</Day>
                <Hour>6</Hour>
                <Minute>0</Minute>
            </PubMedPubDate>
        </History>
        <PublicationStatus>ppublish</PublicationStatus>
        <ArticleIdList>
            <ArticleId IdType="pubmed">24802054</ArticleId>
            <ArticleId IdType="pii">S0891-4222(14)00155-3</ArticleId>
            <ArticleId IdType="doi">10.1016/j.ridd.2014.04.006</ArticleId>
        </ArticleIdList>
    </PubmedData>
</PubmedArticle>

</PubmedArticleSet>
