<?xml version="1.0" ?>
<!DOCTYPE PubmedArticleSet PUBLIC "-//NLM//DTD PubMedArticle, 1st January 2019//EN" "https://dtd.nlm.nih.gov/ncbi/pubmed/out/pubmed_190101.dtd">
<PubmedArticleSet>
<PubmedArticle>
    <MedlineCitation Status="MEDLINE" Owner="NLM">
        <PMID Version="1">9914632</PMID>
        <DateCompleted>
            <Year>1999</Year>
            <Month>02</Month>
            <Day>22</Day>
        </DateCompleted>
        <DateRevised>
            <Year>2019</Year>
            <Month>06</Month>
            <Day>15</Day>
        </DateRevised>
        <Article PubModel="Print">
            <Journal>
                <ISSN IssnType="Print">0002-9378</ISSN>
                <JournalIssue CitedMedium="Print">
                    <Volume>180</Volume>
                    <Issue>1 Pt 3</Issue>
                    <PubDate>
                        <Year>1999</Year>
                        <Month>Jan</Month>
                    </PubDate>
                </JournalIssue>
                <Title>American journal of obstetrics and gynecology</Title>
                <ISOAbbreviation>Am J Obstet Gynecol</ISOAbbreviation>
            </Journal>
            <ArticleTitle>Corticotropin-releasing hormone and the fetoplacental clock: an Australian perspective.</ArticleTitle>
            <Pagination>
                <MedlinePgn>S269-71</MedlinePgn>
            </Pagination>
            <AuthorList CompleteYN="Y">
                <Author ValidYN="Y">
                    <LastName>Smith</LastName>
                    <ForeName>R</ForeName>
                    <Initials>R</Initials>
                    <AffiliationInfo>
                        <Affiliation>Maternal Health Research Centre, John Hunter Hospital, Newcastle, Australia.</Affiliation>
                    </AffiliationInfo>
                </Author>
            </AuthorList>
            <Language>eng</Language>
            <PublicationTypeList>
                <PublicationType UI="D016428">Journal Article</PublicationType>
                <PublicationType UI="D016454">Review</PublicationType>
            </PublicationTypeList>
        </Article>
        <MedlineJournalInfo>
            <Country>United States</Country>
            <MedlineTA>Am J Obstet Gynecol</MedlineTA>
            <NlmUniqueID>0370476</NlmUniqueID>
            <ISSNLinking>0002-9378</ISSNLinking>
        </MedlineJournalInfo>
        <ChemicalList>
            <Chemical>
                <RegistryNumber>9015-71-8</RegistryNumber>
                <NameOfSubstance UI="D003346">Corticotropin-Releasing Hormone</NameOfSubstance>
            </Chemical>
        </ChemicalList>
        <CitationSubset>AIM</CitationSubset>
        <CitationSubset>IM</CitationSubset>
        <MeshHeadingList>
            <MeshHeading>
                <DescriptorName UI="D000818" MajorTopicYN="N">Animals</DescriptorName>
            </MeshHeading>
            <MeshHeading>
                <DescriptorName UI="D001683" MajorTopicYN="N">Biological Clocks</DescriptorName>
                <QualifierName UI="Q000502" MajorTopicYN="Y">physiology</QualifierName>
            </MeshHeading>
            <MeshHeading>
                <DescriptorName UI="D003346" MajorTopicYN="N">Corticotropin-Releasing Hormone</DescriptorName>
                <QualifierName UI="Q000502" MajorTopicYN="Y">physiology</QualifierName>
            </MeshHeading>
            <MeshHeading>
                <DescriptorName UI="D005260" MajorTopicYN="N">Female</DescriptorName>
            </MeshHeading>
            <MeshHeading>
                <DescriptorName UI="D005333" MajorTopicYN="N">Fetus</DescriptorName>
                <QualifierName UI="Q000502" MajorTopicYN="Y">physiology</QualifierName>
            </MeshHeading>
            <MeshHeading>
                <DescriptorName UI="D006801" MajorTopicYN="N">Humans</DescriptorName>
            </MeshHeading>
            <MeshHeading>
                <DescriptorName UI="D010920" MajorTopicYN="N">Placenta</DescriptorName>
                <QualifierName UI="Q000502" MajorTopicYN="Y">physiology</QualifierName>
            </MeshHeading>
            <MeshHeading>
                <DescriptorName UI="D011247" MajorTopicYN="N">Pregnancy</DescriptorName>
            </MeshHeading>
        </MeshHeadingList>
        <NumberOfReferences>23</NumberOfReferences>
    </MedlineCitation>
    <PubmedData>
        <History>
            <PubMedPubDate PubStatus="pubmed">
                <Year>1999</Year>
                <Month>1</Month>
                <Day>23</Day>
            </PubMedPubDate>
            <PubMedPubDate PubStatus="medline">
                <Year>1999</Year>
                <Month>1</Month>
                <Day>23</Day>
                <Hour>0</Hour>
                <Minute>1</Minute>
            </PubMedPubDate>
            <PubMedPubDate PubStatus="entrez">
                <Year>1999</Year>
                <Month>1</Month>
                <Day>23</Day>
                <Hour>0</Hour>
                <Minute>0</Minute>
            </PubMedPubDate>
        </History>
        <PublicationStatus>ppublish</PublicationStatus>
        <ArticleIdList>
            <ArticleId IdType="pubmed">9914632</ArticleId>
            <ArticleId IdType="pii">S0002-9378(99)70715-5</ArticleId>
            <ArticleId IdType="doi">10.1016/s0002-9378(99)70715-5</ArticleId>
        </ArticleIdList>
    </PubmedData>
</PubmedArticle>

</PubmedArticleSet>
